zen_trainer/__init__.py
zen_trainer/benchmark.py
zen_trainer/models.py
zen_trainer/trainer.py
zen_trainer-0.1.0.dist-info/METADATA
zen_trainer-0.1.0.dist-info/WHEEL
zen_trainer-0.1.0.dist-info/entry_points.txt
zen_trainer-0.1.0.dist-info/RECORD
