Metadata-Version: 2.4
Name: zen-trainer
Version: 0.1.0
Summary: Training framework for Zen Coder models - fine-tune 4B to 1T parameter models on agentic coding data
Project-URL: Homepage, https://github.com/zenlm/zen-trainer
Project-URL: Documentation, https://github.com/zenlm/zen-trainer#readme
Project-URL: Repository, https://github.com/zenlm/zen-trainer
Project-URL: Issues, https://github.com/zenlm/zen-trainer/issues
Author-email: Zach Kelling <z@hanzo.ai>
License-Expression: Apache-2.0
Keywords: agentic,coding,devstral,fine-tuning,glm,kimi,llm,qwen,training
Classifier: Development Status :: 3 - Alpha
Classifier: Intended Audience :: Developers
Classifier: Intended Audience :: Science/Research
Classifier: License :: OSI Approved :: Apache Software License
Classifier: Programming Language :: Python :: 3
Classifier: Programming Language :: Python :: 3.10
Classifier: Programming Language :: Python :: 3.11
Classifier: Programming Language :: Python :: 3.12
Classifier: Topic :: Scientific/Engineering :: Artificial Intelligence
Requires-Python: >=3.10
Requires-Dist: accelerate>=0.30.0
Requires-Dist: bitsandbytes>=0.43.0
Requires-Dist: datasets>=2.18.0
Requires-Dist: peft>=0.10.0
Requires-Dist: tiktoken>=0.6.0
Requires-Dist: torch>=2.0.0
Requires-Dist: transformers>=4.40.0
Requires-Dist: trl>=0.8.0
Provides-Extra: all
Requires-Dist: anthropic>=0.20.0; extra == 'all'
Requires-Dist: deepspeed>=0.14.0; extra == 'all'
Requires-Dist: lm-eval>=0.4.0; extra == 'all'
Requires-Dist: mlx-lm>=0.10.0; extra == 'all'
Requires-Dist: mlx>=0.10.0; extra == 'all'
Requires-Dist: openai>=1.0.0; extra == 'all'
Requires-Dist: unsloth>=2024.4; extra == 'all'
Provides-Extra: deepspeed
Requires-Dist: deepspeed>=0.14.0; extra == 'deepspeed'
Provides-Extra: eval
Requires-Dist: anthropic>=0.20.0; extra == 'eval'
Requires-Dist: lm-eval>=0.4.0; extra == 'eval'
Requires-Dist: openai>=1.0.0; extra == 'eval'
Provides-Extra: mlx
Requires-Dist: mlx-lm>=0.10.0; extra == 'mlx'
Requires-Dist: mlx>=0.10.0; extra == 'mlx'
Provides-Extra: unsloth
Requires-Dist: unsloth>=2024.4; extra == 'unsloth'
